CMBPAInT/CMB_PAInT.py
CMBPAInT/__init__.py
CMBPAInT/__version.py
CMBPAInT/Tools/cholesky_tools.py
CMBPAInT/Tools/covariance_tools.py
CMBPAInT/Tools/inpainting_tools.py
CMBPAInT/scripts/cholesky.py
CMBPAInT/scripts/cluster_covariance_matrix.py
CMBPAInT/scripts/cluster_inpainting.py
CMBPAInT/scripts/local_covariance_matrix.py
CMBPAInT/scripts/local_inpainting.py
CMBPAInT-0.1.2.dist-info/LICENSE
CMBPAInT-0.1.2.dist-info/METADATA
CMBPAInT-0.1.2.dist-info/WHEEL
CMBPAInT-0.1.2.dist-info/top_level.txt
CMBPAInT-0.1.2.dist-info/RECORD
